iolanta_tables/__init__.py
iolanta_tables/data/context.yaml
iolanta_tables/data/iolanta-tables.yaml
iolanta_tables/facets/__init__.py
iolanta_tables/facets/cli/__init__.py
iolanta_tables/facets/csv/__init__.py
iolanta_tables/facets/html/__init__.py
iolanta_tables/facets/html/base.py
iolanta_tables/facets/html/body_class.py
iolanta_tables/facets/html/body_rows.py
iolanta_tables/facets/html/errors.py
iolanta_tables/facets/html/header.py
iolanta_tables/facets/html/models.py
iolanta_tables/facets/html/queries.py
iolanta_tables/facets/html/row.py
iolanta_tables/facets/html/self.py
iolanta_tables/facets/html/sparql/column_list_by_row_list.sparql
iolanta_tables/facets/html/sparql/columns.sparql
iolanta_tables/facets/html/sparql/columns_list.sparql
iolanta_tables/facets/html/sparql/instance_class.sparql
iolanta_tables/facets/html/sparql/instances-class.sparql
iolanta_tables/facets/html/sparql/order-by.sparql
iolanta_tables/facets/html/sparql/table_rows.sparql
iolanta_tables/facets/html/sparql/tr.sparql
iolanta_tables/facets/html/table.py
iolanta_tables/facets/json/__init__.py
iolanta_tables/facets/tex/__init__.py
iolanta_tables/models.py
iolanta_tables/plugin.py
iolanta_tables-0.1.7.dist-info/METADATA
iolanta_tables-0.1.7.dist-info/entry_points.txt
iolanta_tables-0.1.7.dist-info/WHEEL
iolanta_tables-0.1.7.dist-info/RECORD
