Metadata-Version: 2.1
Name: iolanta-tables
Version: 0.1.7
Summary: Linked Data as tables
License: MIT
Author: Anatoly Scherbakov
Author-email: altaisoft@gmail.com
Requires-Python: >=3.10,<4.0
Classifier: License :: OSI Approved :: MIT License
Classifier: Programming Language :: Python :: 3
Classifier: Programming Language :: Python :: 3.10
Classifier: Programming Language :: Python :: 3.11
Requires-Dist: dominate (>=2.7.0,<3.0.0)
Requires-Dist: iolanta (>=1.0.11,<2.0.0)
